{
  "dataset": "Quake_10x_Spleen",
  "n_cells": 9552,
  "n_input_features": 2000,
  "n_label_classes": 5,
  "args": {
    "dataset": "Quake_10x_Spleen",
    "epochs": 400,
    "lr": 0.003,
    "temperature": 0.6,
    "dropout": 0.9,
    "dropout_weak": 0.9,
    "dropout_strong": 0.9,
    "layers": [
      200,
      40,
      60,
      40
    ],
    "batch_size": 512,
    "m": 0.5,
    "lambda_i": 1.0,
    "lambda_c": 1.0,
    "lambda_p": 1.0,
    "k": 0.9,
    "n_neighbors": 9,
    "noise": 0.0,
    "log_name": "Quake_10x_Spleen_temperature_0.6_dropout0.9_2026061214"
  },
  "results": [
    {
      "method": "scRGCL",
      "n_clusters": 5,
      "acc": 0.8767797319932998,
      "nmi": 0.6287627391608663,
      "ari": 0.8162359328221906
    }
  ]
}